{
  "noiseKey": {
    "private": {
      "type": "Buffer",
      "data": "wG/PVZiYPpMZZVcs9iH69NjNpe5UChVoFnyQV4cseWI="
    },
    "public": {
      "type": "Buffer",
      "data": "6HpYa2yvN2TdiJGQIH+emeNIbPxe173OsVaPTNJDTgQ="
    }
  },
  "pairingEphemeralKeyPair": {
    "private": {
      "type": "Buffer",
      "data": "CFcAikiIySZf/Gfk5XOubxdiwRQFFwh6mQn1IEv8YVE="
    },
    "public": {
      "type": "Buffer",
      "data": "/RTegp54BTvrPWGw3SwN6cqr7GRtEI/pRZ0UMVi4NCU="
    }
  },
  "signedIdentityKey": {
    "private": {
      "type": "Buffer",
      "data": "eP8QQ7p3IX8B/wMAUn4FemKGcU9B1oQPPN6xrBQxKXo="
    },
    "public": {
      "type": "Buffer",
      "data": "iwWOdUeIluYeQ9CpHrSPLZy/L8By87YG8E9wql26SVc="
    }
  },
  "signedPreKey": {
    "keyPair": {
      "private": {
        "type": "Buffer",
        "data": "OH0B3Kq09h2pqeszCvogC+dhtlUV42Q990qYkCa5Qnw="
      },
      "public": {
        "type": "Buffer",
        "data": "fG006yFq0BNxHdZ8KxcJQgK61rGimB3A7O6xzIupJEE="
      }
    },
    "signature": {
      "type": "Buffer",
      "data": "YVElNdAQSnh9hsnt7milL5FNgul8K3RIXseSO3yEJHR34WipQSnz50NrTgG5W/djLJj3lXmZXnbxacqVktptgA=="
    },
    "keyId": 1
  },
  "registrationId": 5,
  "advSecretKey": "ST4s2mmAP7kbS8PMnqbxD9/FecolF3yBpi15O8/IgIg=",
  "processedHistoryMessages": [
    {
      "key": {
        "remoteJid": "22898312333@s.whatsapp.net",
        "fromMe": true,
        "id": "AC5BE6DCEA4684CD2EE6D72505E7531E",
        "senderLid": "133028743495814:69@lid",
        "senderPn": "22898312333@s.whatsapp.net",
        "addressingMode": "pn"
      },
      "messageTimestamp": 1774614937
    },
    {
      "key": {
        "remoteJid": "22898312333@s.whatsapp.net",
        "fromMe": true,
        "id": "AC274C08E0DF465A335A20279A0AA96D",
        "senderLid": "133028743495814:69@lid",
        "senderPn": "22898312333@s.whatsapp.net",
        "addressingMode": "pn"
      },
      "messageTimestamp": 1774614940
    }
  ],
  "nextPreKeyId": 31,
  "firstUnuploadedPreKeyId": 31,
  "accountSyncCounter": 1,
  "accountSettings": {
    "unarchiveChats": false
  },
  "registered": true,
  "pairingCode": "Y79H4Z7K",
  "me": {
    "id": "22898312333:69@s.whatsapp.net",
    "lid": "133028743495814:69@lid",
    "name": "JOHN_VERSE🫧"
  },
  "account": {
    "details": "CMyo45ABEIvzmc4GGAEgACgA",
    "accountSignatureKey": "da56u1x/sLr0ufQcce2SpBt4VF2SV3hB0v0/3jr9Mhw=",
    "accountSignature": "OTlrBb0AbwXvwZ6Qf0P6iwV4AsRlez/Uxfv4pWSsIKcZ3blsfWNJHknQFO2quxwemUe67eheaRkTo+kO37WOAQ==",
    "deviceSignature": "iKyOGYgdKfoHYvYiEdXEIVJydh+mKVTkYzeUFcMdKaqLiuotKqzvgl5+q1BiMYR5wNYUZNTAdIfoCIm1uaOnhQ=="
  },
  "signalIdentities": [
    {
      "identifier": {
        "name": "22898312333:69@s.whatsapp.net",
        "deviceId": 0
      },
      "identifierKey": {
        "type": "Buffer",
        "data": "BXWuertcf7C69Ln0HHHtkqQbeFRdkld4QdL9P946/TIc"
      }
    }
  ],
  "platform": "android",
  "routingInfo": {
    "type": "Buffer",
    "data": "CAUIAggI"
  },
  "lastAccountSyncTimestamp": 1774614933,
  "lastPropHash": "3ml1jS",
  "myAppStateKeyId": "AAAAAPmj"
}